coordop/__init__.py
coordop/bibliography.py
coordop/operation.py
coordop/surface.py
coordop/projection/__init__.py
coordop/projection/epsg.py
coordop/projection/map_projections.py
coordop/projection/mercator_spherical.py
coordop/util/__init__.py
coordop/util/integral.py
coordop-0.19.4.dist-info/licenses/LICENSE.md
coordop-0.19.4.dist-info/METADATA
coordop-0.19.4.dist-info/WHEEL
coordop-0.19.4.dist-info/top_level.txt
coordop-0.19.4.dist-info/RECORD
