Metadata-Version: 2.4
Name: coordop
Version: 0.19.4
Summary: Cartography and geodesy formulas.
Author-email: Samuel Andrés <samuel.andres@yahoo.fr>
License: This is free and unencumbered software released into the public domain.
Project-URL: Homepage, https://github.com/SamuelAndresPascal/cosmoloj-py/tree/coordop_0.19.4/coordop
Keywords: epsg,geomatics,cartography,geodesy,projection,mathematics
Classifier: Programming Language :: Python :: 3
Classifier: Operating System :: OS Independent
Classifier: Development Status :: 5 - Production/Stable
Classifier: Intended Audience :: Developers
Classifier: Intended Audience :: Science/Research
Classifier: License :: Public Domain
Classifier: Topic :: Scientific/Engineering
Classifier: Topic :: Software Development
Classifier: Topic :: Utilities
Requires-Python: >=3.12
License-File: LICENSE.md
Requires-Dist: bibliograpy==0.4.0
Dynamic: license-file
